{"errors":[],"warnings":[],"namedChunkGroups":{"app":{"chunks":[9,3],"assets":["webpack-runtime-982ec035e8f6309e7ab9.js","webpack-runtime-982ec035e8f6309e7ab9.js.map","app-f596fb88568716e6aa49.js","app-f596fb88568716e6aa49.js.map"],"children":{},"childAssets":{}},"component---src-pages-404-js":{"chunks":[0,2,1,4],"assets":["0-fbfca57ff26ff4dd0ffa.js","0-fbfca57ff26ff4dd0ffa.js.map","2-0577898f622101aa94f4.js","2-0577898f622101aa94f4.js.map","1.415a55a3d1a29184b840.css","1-fc1ca52a3753f410ba88.js","1-fc1ca52a3753f410ba88.js.map","component---src-pages-404-js-e14b2f7bd594572ba021.js","component---src-pages-404-js-e14b2f7bd594572ba021.js.map"],"children":{},"childAssets":{}},"component---src-pages-index-js":{"chunks":[0,2,1,5],"assets":["0-fbfca57ff26ff4dd0ffa.js","0-fbfca57ff26ff4dd0ffa.js.map","2-0577898f622101aa94f4.js","2-0577898f622101aa94f4.js.map","1.415a55a3d1a29184b840.css","1-fc1ca52a3753f410ba88.js","1-fc1ca52a3753f410ba88.js.map","component---src-pages-index-js-180154b7cf4c8ded7441.js","component---src-pages-index-js-180154b7cf4c8ded7441.js.map"],"children":{},"childAssets":{}},"component---src-pages-person-js":{"chunks":[0,2,10,1,6],"assets":["0-fbfca57ff26ff4dd0ffa.js","0-fbfca57ff26ff4dd0ffa.js.map","2-0577898f622101aa94f4.js","2-0577898f622101aa94f4.js.map","10.f63df79e9bd714cd7745.css","10-e30d3b32cbb86720bd11.js","10-e30d3b32cbb86720bd11.js.map","1.415a55a3d1a29184b840.css","1-fc1ca52a3753f410ba88.js","1-fc1ca52a3753f410ba88.js.map","component---src-pages-person-js.b427e50335e2c5526a51.css","component---src-pages-person-js-271d06d92f12d29655b8.js","component---src-pages-person-js-271d06d92f12d29655b8.js.map"],"children":{},"childAssets":{}},"component---src-pages-team-js":{"chunks":[0,1,7],"assets":["0-fbfca57ff26ff4dd0ffa.js","0-fbfca57ff26ff4dd0ffa.js.map","1.415a55a3d1a29184b840.css","1-fc1ca52a3753f410ba88.js","1-fc1ca52a3753f410ba88.js.map","component---src-pages-team-js-e98f67d58dbb203cb337.js","component---src-pages-team-js-e98f67d58dbb203cb337.js.map"],"children":{},"childAssets":{}},"pages-manifest":{"chunks":[8],"assets":["pages-manifest-06662feb3aa0c36b8401.js","pages-manifest-06662feb3aa0c36b8401.js.map"],"children":{},"childAssets":{}}},"assetsByChunkName":{"app":["webpack-runtime-982ec035e8f6309e7ab9.js","app-f596fb88568716e6aa49.js"],"component---src-pages-404-js":["0-fbfca57ff26ff4dd0ffa.js","2-0577898f622101aa94f4.js","1.415a55a3d1a29184b840.css","1-fc1ca52a3753f410ba88.js","component---src-pages-404-js-e14b2f7bd594572ba021.js"],"component---src-pages-index-js":["0-fbfca57ff26ff4dd0ffa.js","2-0577898f622101aa94f4.js","1.415a55a3d1a29184b840.css","1-fc1ca52a3753f410ba88.js","component---src-pages-index-js-180154b7cf4c8ded7441.js"],"component---src-pages-person-js":["0-fbfca57ff26ff4dd0ffa.js","2-0577898f622101aa94f4.js","10.f63df79e9bd714cd7745.css","10-e30d3b32cbb86720bd11.js","1.415a55a3d1a29184b840.css","1-fc1ca52a3753f410ba88.js","component---src-pages-person-js.b427e50335e2c5526a51.css","component---src-pages-person-js-271d06d92f12d29655b8.js"],"component---src-pages-team-js":["0-fbfca57ff26ff4dd0ffa.js","1.415a55a3d1a29184b840.css","1-fc1ca52a3753f410ba88.js","component---src-pages-team-js-e98f67d58dbb203cb337.js"],"pages-manifest":["pages-manifest-06662feb3aa0c36b8401.js"]}}